gammarer/aws_secure_flow_log_bucket/__init__.py
gammarer/aws_secure_flow_log_bucket/py.typed
gammarer/aws_secure_flow_log_bucket/_jsii/__init__.py
gammarer/aws_secure_flow_log_bucket/_jsii/aws-secure-flow-log-bucket@1.3.6.jsii.tgz
gammarer.aws_secure_flow_log_bucket-1.3.6.dist-info/LICENSE
gammarer.aws_secure_flow_log_bucket-1.3.6.dist-info/METADATA
gammarer.aws_secure_flow_log_bucket-1.3.6.dist-info/WHEEL
gammarer.aws_secure_flow_log_bucket-1.3.6.dist-info/top_level.txt
gammarer.aws_secure_flow_log_bucket-1.3.6.dist-info/RECORD
