Metadata-Version: 2.1
Name: gammarer.aws-secure-flow-log-bucket
Version: 1.3.6
Summary: Specific AWS VPC FlowLog Bucket
Home-page: https://github.com/gammarer/aws-secure-flow-log-bucket.git
Author: yicr<yicr@users.noreply.github.com>
License: Apache-2.0
Project-URL: Source, https://github.com/gammarer/aws-secure-flow-log-bucket.git
Classifier: Intended Audience :: Developers
Classifier: Operating System :: OS Independent
Classifier: Programming Language :: JavaScript
Classifier: Programming Language :: Python :: 3 :: Only
Classifier: Programming Language :: Python :: 3.8
Classifier: Programming Language :: Python :: 3.9
Classifier: Programming Language :: Python :: 3.10
Classifier: Programming Language :: Python :: 3.11
Classifier: Typing :: Typed
Classifier: Development Status :: 5 - Production/Stable
Classifier: License :: OSI Approved
Requires-Python: ~=3.8
License-File: LICENSE
Requires-Dist: aws-cdk-lib <3.0.0,>=2.80.0
Requires-Dist: constructs <11.0.0,>=10.0.5
Requires-Dist: gammarer.aws-secure-bucket <1.2.0,>=1.1.0
Requires-Dist: gammarer.aws-secure-log-bucket <1.3.0,>=1.2.0
Requires-Dist: jsii <2.0.0,>=1.97.0
Requires-Dist: publication >=0.0.3
Requires-Dist: typeguard ~=2.13.3
